{"textures":[{"image":"first-10-levels-game-objects-resources.png","format":"RGBA8888","size":{"w":254,"h":1164},"scale":1,"frames":[{"filename":"shot-guide/rainbow/straight","rotated":false,"trimmed":false,"sourceSize":{"w":221,"h":37},"spriteSourceSize":{"x":0,"y":0,"w":221,"h":37},"frame":{"x":2,"y":2,"w":221,"h":37}},{"filename":"shooter","rotated":false,"trimmed":false,"sourceSize":{"w":182,"h":182},"spriteSourceSize":{"x":0,"y":0,"w":182,"h":182},"frame":{"x":2,"y":42,"w":182,"h":182}},{"filename":"gem-ball/gem_green","rotated":false,"trimmed":false,"sourceSize":{"w":62,"h":59},"spriteSourceSize":{"x":0,"y":0,"w":62,"h":59},"frame":{"x":187,"y":42,"w":62,"h":59}},{"filename":"gem-ball/gem_blue","rotated":false,"trimmed":false,"sourceSize":{"w":61,"h":63},"spriteSourceSize":{"x":0,"y":0,"w":61,"h":63},"frame":{"x":187,"y":104,"w":61,"h":63}},{"filename":"gem-ball/gem_pink","rotated":false,"trimmed":false,"sourceSize":{"w":61,"h":61},"spriteSourceSize":{"x":0,"y":0,"w":61,"h":61},"frame":{"x":187,"y":170,"w":61,"h":61}},{"filename":"shot-guide/curve","rotated":false,"trimmed":false,"sourceSize":{"w":160,"h":38},"spriteSourceSize":{"x":0,"y":0,"w":160,"h":38},"frame":{"x":2,"y":227,"w":160,"h":38}},{"filename":"bomb-drug/bomb-drug","rotated":false,"trimmed":false,"sourceSize":{"w":69,"h":71},"spriteSourceSize":{"x":0,"y":0,"w":69,"h":71},"frame":{"x":165,"y":234,"w":69,"h":71}},{"filename":"bubbles/thunder-ball-glow","rotated":false,"trimmed":false,"sourceSize":{"w":127,"h":127},"spriteSourceSize":{"x":0,"y":0,"w":127,"h":127},"frame":{"x":2,"y":268,"w":127,"h":127}},{"filename":"highlight-circle","rotated":false,"trimmed":false,"sourceSize":{"w":118,"h":118},"spriteSourceSize":{"x":0,"y":0,"w":118,"h":118},"frame":{"x":132,"y":308,"w":118,"h":118}},{"filename":"glow03","rotated":false,"trimmed":false,"sourceSize":{"w":122,"h":122},"spriteSourceSize":{"x":0,"y":0,"w":122,"h":122},"frame":{"x":2,"y":398,"w":122,"h":122}},{"filename":"curve-arrow","rotated":false,"trimmed":false,"sourceSize":{"w":122,"h":65},"spriteSourceSize":{"x":0,"y":0,"w":122,"h":65},"frame":{"x":127,"y":429,"w":122,"h":65}},{"filename":"blank","rotated":false,"trimmed":false,"sourceSize":{"w":100,"h":100},"spriteSourceSize":{"x":0,"y":0,"w":100,"h":100},"frame":{"x":127,"y":497,"w":100,"h":100}},{"filename":"shot-guide/bullet-item-simulator","rotated":false,"trimmed":false,"sourceSize":{"w":93,"h":93},"spriteSourceSize":{"x":0,"y":0,"w":93,"h":93},"frame":{"x":2,"y":523,"w":93,"h":93}},{"filename":"thunder/thunder","rotated":false,"trimmed":false,"sourceSize":{"w":69,"h":68},"spriteSourceSize":{"x":0,"y":0,"w":69,"h":68},"frame":{"x":98,"y":600,"w":69,"h":68}},{"filename":"bubbles/ball_blue","rotated":false,"trimmed":false,"sourceSize":{"w":68,"h":68},"spriteSourceSize":{"x":0,"y":0,"w":68,"h":68},"frame":{"x":170,"y":600,"w":68,"h":68}},{"filename":"bubbles/ball_cyan","rotated":false,"trimmed":false,"sourceSize":{"w":68,"h":68},"spriteSourceSize":{"x":0,"y":0,"w":68,"h":68},"frame":{"x":2,"y":619,"w":68,"h":68}},{"filename":"bubbles/ball_green","rotated":false,"trimmed":false,"sourceSize":{"w":68,"h":68},"spriteSourceSize":{"x":0,"y":0,"w":68,"h":68},"frame":{"x":73,"y":671,"w":68,"h":68}},{"filename":"bubbles/ball_orange","rotated":false,"trimmed":false,"sourceSize":{"w":68,"h":68},"spriteSourceSize":{"x":0,"y":0,"w":68,"h":68},"frame":{"x":2,"y":690,"w":68,"h":68}},{"filename":"bubbles/ball_pink","rotated":false,"trimmed":false,"sourceSize":{"w":68,"h":68},"spriteSourceSize":{"x":0,"y":0,"w":68,"h":68},"frame":{"x":144,"y":671,"w":68,"h":68}},{"filename":"shot-guide/blue/straight","rotated":false,"trimmed":false,"sourceSize":{"w":37,"h":37},"spriteSourceSize":{"x":0,"y":0,"w":37,"h":37},"frame":{"x":215,"y":671,"w":37,"h":37}},{"filename":"shot-guide/bomb/straight","rotated":false,"trimmed":false,"sourceSize":{"w":37,"h":37},"spriteSourceSize":{"x":0,"y":0,"w":37,"h":37},"frame":{"x":215,"y":711,"w":37,"h":37}},{"filename":"bubbles/ball_red","rotated":false,"trimmed":false,"sourceSize":{"w":68,"h":68},"spriteSourceSize":{"x":0,"y":0,"w":68,"h":68},"frame":{"x":73,"y":742,"w":68,"h":68}},{"filename":"bubbles/ball_violet","rotated":false,"trimmed":false,"sourceSize":{"w":68,"h":68},"spriteSourceSize":{"x":0,"y":0,"w":68,"h":68},"frame":{"x":2,"y":761,"w":68,"h":68}},{"filename":"bubbles/ball_yellow","rotated":false,"trimmed":false,"sourceSize":{"w":68,"h":68},"spriteSourceSize":{"x":0,"y":0,"w":68,"h":68},"frame":{"x":144,"y":742,"w":68,"h":68}},{"filename":"shot-guide/cyan/straight","rotated":false,"trimmed":false,"sourceSize":{"w":37,"h":37},"spriteSourceSize":{"x":0,"y":0,"w":37,"h":37},"frame":{"x":215,"y":751,"w":37,"h":37}},{"filename":"shot-guide/electric/straight","rotated":false,"trimmed":false,"sourceSize":{"w":37,"h":37},"spriteSourceSize":{"x":0,"y":0,"w":37,"h":37},"frame":{"x":215,"y":791,"w":37,"h":37}},{"filename":"bubbles/ball_transparent","rotated":false,"trimmed":false,"sourceSize":{"w":67,"h":69},"spriteSourceSize":{"x":0,"y":0,"w":67,"h":69},"frame":{"x":73,"y":813,"w":67,"h":69}},{"filename":"gem-ball/gem_cyan","rotated":false,"trimmed":false,"sourceSize":{"w":61,"h":60},"spriteSourceSize":{"x":0,"y":0,"w":61,"h":60},"frame":{"x":2,"y":832,"w":61,"h":60}},{"filename":"gem-ball/gem_orange","rotated":false,"trimmed":false,"sourceSize":{"w":61,"h":60},"spriteSourceSize":{"x":0,"y":0,"w":61,"h":60},"frame":{"x":143,"y":813,"w":61,"h":60}},{"filename":"shot-guide/green/straight","rotated":false,"trimmed":false,"sourceSize":{"w":37,"h":37},"spriteSourceSize":{"x":0,"y":0,"w":37,"h":37},"frame":{"x":207,"y":831,"w":37,"h":37}},{"filename":"shot-guide/orange/straight","rotated":false,"trimmed":false,"sourceSize":{"w":37,"h":37},"spriteSourceSize":{"x":0,"y":0,"w":37,"h":37},"frame":{"x":207,"y":871,"w":37,"h":37}},{"filename":"gem-ball/gem_purple","rotated":false,"trimmed":false,"sourceSize":{"w":61,"h":60},"spriteSourceSize":{"x":0,"y":0,"w":61,"h":60},"frame":{"x":143,"y":876,"w":61,"h":60}},{"filename":"shot-guide/pink/straight","rotated":false,"trimmed":false,"sourceSize":{"w":37,"h":37},"spriteSourceSize":{"x":0,"y":0,"w":37,"h":37},"frame":{"x":207,"y":911,"w":37,"h":37}},{"filename":"gem-ball/gem_yellow","rotated":false,"trimmed":false,"sourceSize":{"w":61,"h":60},"spriteSourceSize":{"x":0,"y":0,"w":61,"h":60},"frame":{"x":66,"y":885,"w":61,"h":60}},{"filename":"gem-ball/gem_red","rotated":false,"trimmed":false,"sourceSize":{"w":61,"h":59},"spriteSourceSize":{"x":0,"y":0,"w":61,"h":59},"frame":{"x":2,"y":895,"w":61,"h":59}},{"filename":"shot-guide/blue/bg_point","rotated":false,"trimmed":false,"sourceSize":{"w":54,"h":55},"spriteSourceSize":{"x":0,"y":0,"w":54,"h":55},"frame":{"x":130,"y":939,"w":54,"h":55}},{"filename":"shot-guide/bomb/bg_point","rotated":false,"trimmed":false,"sourceSize":{"w":54,"h":55},"spriteSourceSize":{"x":0,"y":0,"w":54,"h":55},"frame":{"x":66,"y":948,"w":54,"h":55}},{"filename":"shot-guide/cyan/bg_point","rotated":false,"trimmed":false,"sourceSize":{"w":54,"h":55},"spriteSourceSize":{"x":0,"y":0,"w":54,"h":55},"frame":{"x":2,"y":957,"w":54,"h":55}},{"filename":"shot-guide/electric/bg_point","rotated":false,"trimmed":false,"sourceSize":{"w":54,"h":55},"spriteSourceSize":{"x":0,"y":0,"w":54,"h":55},"frame":{"x":187,"y":951,"w":54,"h":55}},{"filename":"shot-guide/green/bg_point","rotated":false,"trimmed":false,"sourceSize":{"w":54,"h":55},"spriteSourceSize":{"x":0,"y":0,"w":54,"h":55},"frame":{"x":123,"y":997,"w":54,"h":55}},{"filename":"shot-guide/orange/bg_point","rotated":false,"trimmed":false,"sourceSize":{"w":54,"h":55},"spriteSourceSize":{"x":0,"y":0,"w":54,"h":55},"frame":{"x":59,"y":1006,"w":54,"h":55}},{"filename":"shot-guide/pink/bg_point","rotated":false,"trimmed":false,"sourceSize":{"w":54,"h":55},"spriteSourceSize":{"x":0,"y":0,"w":54,"h":55},"frame":{"x":2,"y":1015,"w":54,"h":55}},{"filename":"shot-guide/rainbow/bg_point","rotated":false,"trimmed":false,"sourceSize":{"w":54,"h":55},"spriteSourceSize":{"x":0,"y":0,"w":54,"h":55},"frame":{"x":180,"y":1009,"w":54,"h":55}},{"filename":"shot-guide/red/bg_point","rotated":false,"trimmed":false,"sourceSize":{"w":54,"h":55},"spriteSourceSize":{"x":0,"y":0,"w":54,"h":55},"frame":{"x":116,"y":1055,"w":54,"h":55}},{"filename":"shot-guide/rocket/bg_point","rotated":false,"trimmed":false,"sourceSize":{"w":54,"h":55},"spriteSourceSize":{"x":0,"y":0,"w":54,"h":55},"frame":{"x":59,"y":1064,"w":54,"h":55}},{"filename":"shot-guide/violet/bg_point","rotated":false,"trimmed":false,"sourceSize":{"w":54,"h":55},"spriteSourceSize":{"x":0,"y":0,"w":54,"h":55},"frame":{"x":2,"y":1073,"w":54,"h":55}},{"filename":"shot-guide/red/straight","rotated":false,"trimmed":false,"sourceSize":{"w":37,"h":37},"spriteSourceSize":{"x":0,"y":0,"w":37,"h":37},"frame":{"x":59,"y":1122,"w":37,"h":37}},{"filename":"shot-guide/rocket/straight","rotated":false,"trimmed":false,"sourceSize":{"w":37,"h":37},"spriteSourceSize":{"x":0,"y":0,"w":37,"h":37},"frame":{"x":99,"y":1122,"w":37,"h":37}},{"filename":"shot-guide/violet/straight","rotated":false,"trimmed":false,"sourceSize":{"w":37,"h":37},"spriteSourceSize":{"x":0,"y":0,"w":37,"h":37},"frame":{"x":139,"y":1113,"w":37,"h":37}},{"filename":"shot-guide/yellow/straight","rotated":false,"trimmed":false,"sourceSize":{"w":37,"h":37},"spriteSourceSize":{"x":0,"y":0,"w":37,"h":37},"frame":{"x":173,"y":1067,"w":37,"h":37}},{"filename":"shot-guide/yellow/bg_point","rotated":false,"trimmed":false,"sourceSize":{"w":54,"h":55},"spriteSourceSize":{"x":0,"y":0,"w":54,"h":55},"frame":{"x":179,"y":1107,"w":54,"h":55}}]}],"meta":{"app":"https://www.codeandweb.com/texturepacker","version":"3.0","smartupdate":"$TexturePacker:SmartUpdate:700621d88f7919b744ef8dc7b96571d6:68f5176696c415109f944c513d6b8b58:0996dd7e9db609960a6dcf09e17bc364$"}}